dwncode/__init__.py
dwncode/_init_.py
dwncode-0.22.dist-info/Licence.txt.txt
dwncode-0.22.dist-info/METADATA
dwncode-0.22.dist-info/WHEEL
dwncode-0.22.dist-info/top_level.txt
dwncode-0.22.dist-info/RECORD
