Metadata-Version: 2.1
Name: dwncode
Version: 0.22
Summary: Dwn Code
Author: JOD
License: UNKNOWN
Platform: UNKNOWN
License-File: Licence.txt.txt
